inferno/__init__.py
inferno/_internal/__init__.py
inferno/_internal/argtest.py
inferno/_internal/utils.py
inferno/core/__init__.py
inferno/core/infrastructure.py
inferno/core/math.py
inferno/core/tensor.py
inferno/core/trace.py
inferno/extra/__init__.py
inferno/extra/functional.py
inferno/extra/neural.py
inferno/functional/__init__.py
inferno/functional/bounding.py
inferno/functional/dimreductiion.py
inferno/functional/extrapolation.py
inferno/functional/interpolation.py
inferno/functional/protocols.py
inferno/functional/stdkernels.py
inferno/learn/__init__.py
inferno/learn/base.py
inferno/learn/classifiers/__init__.py
inferno/learn/classifiers/simple.py
inferno/learn/trainers/__init__.py
inferno/learn/trainers/delay_adj_three_factor_stdp.py
inferno/learn/trainers/delay_adj_two_factor_stdp.py
inferno/learn/trainers/homeostasis.py
inferno/learn/trainers/kernel_stdp.py
inferno/learn/trainers/three_factor_stdp.py
inferno/learn/trainers/two_factor_stdp.py
inferno/neural/__init__.py
inferno/neural/base.py
inferno/neural/hooks.py
inferno/neural/mixins.py
inferno/neural/modeling.py
inferno/neural/network.py
inferno/neural/connections/__init__.py
inferno/neural/connections/conv.py
inferno/neural/connections/linear.py
inferno/neural/connections/mixins.py
inferno/neural/encoders/mixins.py
inferno/neural/encoders/poisson.py
inferno/neural/encoders/special.py
inferno/neural/functional/__init__.py
inferno/neural/functional/encoding.py
inferno/neural/functional/neuron_adaptation.py
inferno/neural/functional/neuron_dynamics.py
inferno/neural/neurons/__init__.py
inferno/neural/neurons/linear.py
inferno/neural/neurons/mixins.py
inferno/neural/neurons/nonlinear.py
inferno/neural/synapses/__init__.py
inferno/neural/synapses/current.py
inferno/neural/synapses/expcurrent.py
inferno/neural/synapses/mixins.py
inferno/observe/__init__.py
inferno/observe/monitors.py
inferno/observe/pooling.py
inferno/observe/reducers/__init__.py
inferno/observe/reducers/base.py
inferno_ai-0.0.5.dist-info/METADATA
inferno_ai-0.0.5.dist-info/WHEEL
inferno_ai-0.0.5.dist-info/licenses/LICENSE
inferno_ai-0.0.5.dist-info/RECORD
