Metadata-Version: 2.3
Name: inferno-ai
Version: 0.0.5
Summary: An Extensible Spiking Neural Network Library
Project-URL: Homepage, https://github.com/mdominijanni/inferno
Project-URL: Documentation, https://docs.inferno-ai.dev
Author-email: Marissa Dominijanni <mdomini@buffalo.edu>
License: BSD 3-Clause License
License-File: LICENSE
Classifier: Development Status :: 2 - Pre-Alpha
Classifier: License :: OSI Approved :: BSD License
Classifier: Programming Language :: Python :: 3.11
Classifier: Programming Language :: Python :: 3.12
Classifier: Topic :: Scientific/Engineering :: Artificial Intelligence
Classifier: Topic :: Software Development :: Libraries :: Python Modules
Requires-Python: >=3.11
Requires-Dist: einops>=0.7
Requires-Dist: numpy>=1.26
Provides-Extra: torch
Requires-Dist: torch==2.4.1; (sys_platform == 'darwin') and extra == 'torch'
Requires-Dist: torch==2.4.1; (sys_platform == 'linux') and extra == 'torch'
Requires-Dist: torch==2.4.1; (sys_platform == 'win32') and extra == 'torch'
Requires-Dist: torchvision==0.19.1; (sys_platform == 'darwin') and extra == 'torch'
Requires-Dist: torchvision==0.19.1; (sys_platform == 'linux') and extra == 'torch'
Requires-Dist: torchvision==0.19.1; (sys_platform == 'win32') and extra == 'torch'
